jarvis_ipybox/__init__.py
jarvis_ipybox/__main__.py
jarvis_ipybox/config/default/custom_kernel_manager.py
jarvis_ipybox/config/default/dependencies.txt
jarvis_ipybox/config/default/environment.yml
jarvis_ipybox/config/default/jupyter_kernel_gateway_config.py
jarvis_ipybox/config/default/pyproject.toml
jarvis_ipybox/container.py
jarvis_ipybox/docker/Dockerfile
jarvis_ipybox/docker/Dockerfile.root
jarvis_ipybox/executor.py
jarvis_ipybox/modinfo.py
jarvis_ipybox/scripts/cleanup.sh
jarvis_ipybox/scripts/server.sh
jarvis_ipybox/scripts/test.txt
jarvis_ipybox/utils.py
jarvis_ipybox-0.4.13.dist-info/LICENSE
jarvis_ipybox-0.4.13.dist-info/METADATA
jarvis_ipybox-0.4.13.dist-info/WHEEL
jarvis_ipybox-0.4.13.dist-info/RECORD
