Metadata-Version: 2.3
Name: jarvis-ipybox
Version: 0.4.13
Summary: Python code execution sandbox based on IPython and Docker
License: Apache-2.0
Author: Aiden Jang
Author-email: sbjang01@gmail.com
Requires-Python: >=3.11,<3.14
Classifier: License :: OSI Approved :: Apache Software License
Classifier: Programming Language :: Python :: 3
Classifier: Programming Language :: Python :: 3.11
Classifier: Programming Language :: Python :: 3.12
Classifier: Programming Language :: Python :: 3.13
Requires-Dist: aiodocker (>=0.23.0,<0.24.0)
Requires-Dist: aiofiles (>=24.1,<25.0)
Requires-Dist: aiohttp (>=3.10,<4.0)
Requires-Dist: pillow (>=11.0,<12.0)
Requires-Dist: tornado (>=6.4,<7.0)
Requires-Dist: typer (>=0.12.5,<0.13.0)
Project-URL: Homepage, https://github.com/cjcj-dx-lab/jarvis-ipybox
